gopika_adventure_game/__init__.py
gopika_adventure_game/constants.py
gopika_adventure_game/game_engine.py
gopika_adventure_game/main.py
gopika_adventure_game/stage_logic.py
gopika_adventure_game-0.1.0.dist-info/entry_points.txt
gopika_adventure_game-0.1.0.dist-info/METADATA
gopika_adventure_game-0.1.0.dist-info/WHEEL
gopika_adventure_game-0.1.0.dist-info/RECORD
