Metadata-Version: 2.3
Name: gopika-adventure-game
Version: 0.1.0
Summary: A text based adventure game using Rich and Questionary
Author: Gopika Gopalakrishnan
Author-email: you@example.com
Requires-Python: >=3.10
Classifier: Programming Language :: Python :: 3
Classifier: Programming Language :: Python :: 3.10
Classifier: Programming Language :: Python :: 3.11
Classifier: Programming Language :: Python :: 3.12
Classifier: Programming Language :: Python :: 3.13
Requires-Dist: questionary (>=2.1.1,<3.0.0)
Requires-Dist: rich (>=14.1.0,<15.0.0)
